tourbillon_log-0.4.1-py2.7-nspkg.pth
tourbillon/log/__init__.py
tourbillon/log/log.py
tourbillon_log-0.4.1.dist-info/DESCRIPTION.rst
tourbillon_log-0.4.1.dist-info/METADATA
tourbillon_log-0.4.1.dist-info/RECORD
tourbillon_log-0.4.1.dist-info/WHEEL
tourbillon_log-0.4.1.dist-info/metadata.json
tourbillon_log-0.4.1.dist-info/namespace_packages.txt
tourbillon_log-0.4.1.dist-info/top_level.txt
